hermod/__init__.py
hermod/hermod.py
hermod/message.py
hermod/message_field.py
hermod/message_relation.py
hermod-0.1.0.dist-info/LICENSE
hermod-0.1.0.dist-info/WHEEL
hermod-0.1.0.dist-info/METADATA
hermod-0.1.0.dist-info/RECORD
